huuid/__init__.py
huuid-0.8.0.dist-info/LICENSE
huuid-0.8.0.dist-info/METADATA
huuid-0.8.0.dist-info/WHEEL
huuid-0.8.0.dist-info/top_level.txt
huuid-0.8.0.dist-info/RECORD
