Metadata-Version: 2.1
Name: huuid
Version: 0.8.0
Summary: library to convert uuids forth and back to a human-readable and pronounceable format
Home-page: https://github.com/polarwinkel/mdtex2html
Author: Dirk Winkel
Author-email: it@polarwinkel.de
Project-URL: Bug Reports, https://github.com/polarwinkel/mdtex2html/issues
Project-URL: Source, https://github.com/polarwinkel/mdtex2html
Keywords: TeX,LaTeX,Markdown,HTML markdown2html,latex2mathml
Classifier: Development Status :: 5 - Production/Stable
Classifier: Intended Audience :: Developers
Classifier: Environment :: Console
Classifier: Topic :: Database
Classifier: Topic :: Security
Classifier: Topic :: Software Development :: Libraries
Classifier: Topic :: System
Classifier: License :: OSI Approved :: GNU General Public License v3 or later (GPLv3+)
Classifier: Programming Language :: Python :: 3
Classifier: Programming Language :: Python :: 3.7
Classifier: Programming Language :: Python :: 3.8
Classifier: Programming Language :: Python :: 3.9
Classifier: Programming Language :: Python :: 3.10
Classifier: Programming Language :: Python :: 3.11
Classifier: Programming Language :: Python :: 3.12
Classifier: Programming Language :: Python :: 3.13
Classifier: Programming Language :: Python :: 3.14
Classifier: Programming Language :: Python :: 3 :: Only
Requires-Python: >=3.7, <4
License-File: LICENSE
Requires-Dist: markdown
Requires-Dist: latex2mathml
